odoo10_addon_calendar_dst_bug_fix-10.0.1.0.0.99.dev7-py3.8-nspkg.pth
odoo/addons/calendar_dst_bug_fix/README.md
odoo/addons/calendar_dst_bug_fix/README.rst
odoo/addons/calendar_dst_bug_fix/__init__.py
odoo/addons/calendar_dst_bug_fix/__manifest__.py
odoo/addons/calendar_dst_bug_fix/i18n/calendar_dst_bug_fix.pot
odoo/addons/calendar_dst_bug_fix/models/__init__.py
odoo/addons/calendar_dst_bug_fix/models/calendar_event.py
odoo/addons/calendar_dst_bug_fix/readme/CONTRIBUTORS.rst
odoo/addons/calendar_dst_bug_fix/readme/CREDITS.rst
odoo/addons/calendar_dst_bug_fix/readme/DESCRIPTION.rst
odoo/addons/calendar_dst_bug_fix/static/description/icon.png
odoo/addons/calendar_dst_bug_fix/static/description/index.html
odoo/addons/calendar_dst_bug_fix/tests/__init__.py
odoo/addons/calendar_dst_bug_fix/tests/test_calendar_recurrent_event_with_dst.py
odoo10_addon_calendar_dst_bug_fix-10.0.1.0.0.99.dev7.dist-info/METADATA
odoo10_addon_calendar_dst_bug_fix-10.0.1.0.0.99.dev7.dist-info/WHEEL
odoo10_addon_calendar_dst_bug_fix-10.0.1.0.0.99.dev7.dist-info/namespace_packages.txt
odoo10_addon_calendar_dst_bug_fix-10.0.1.0.0.99.dev7.dist-info/top_level.txt
odoo10_addon_calendar_dst_bug_fix-10.0.1.0.0.99.dev7.dist-info/RECORD
